[
  {"id":"b1","name":"Admirals Port","slug":"admirals-port","neighborhoodId":"n1"},
  {"id":"b2","name":"Echo Aventura","slug":"echo-aventura","neighborhoodId":"n1"},
  {"id":"b3","name":"Marina Palms","slug":"marina-palms","neighborhoodId":"n1"},
  {"id":"b4","name":"Turnberry on the Green","slug":"turnberry-on-the-green","neighborhoodId":"n1"},
  {"id":"b5","name":"Hidden Bay","slug":"hidden-bay","neighborhoodId":"n1"},
  {"id":"b6","name":"Porto Vita","slug":"porto-vita","neighborhoodId":"n1"},
  {"id":"b7","name":"Oceana Bal Harbour","slug":"oceana-bal-harbour","neighborhoodId":"n2"},
  {"id":"b8","name":"Ritz Carlton Bal Harbour","slug":"ritz-carlton-bal-harbour","neighborhoodId":"n2"},
  {"id":"b9","name":"St Regis Bal Harbour","slug":"st-regis-bal-harbour","neighborhoodId":"n2"},
  {"id":"b10","name":"Majestic Tower","slug":"majestic-tower","neighborhoodId":"n2"},
  {"id":"b11","name":"Harbour House","slug":"harbour-house","neighborhoodId":"n2"},
  {"id":"b12","name":"Bellini","slug":"bellini","neighborhoodId":"n2"},
  {"id":"b13","name":"Icon Brickell","slug":"icon-brickell","neighborhoodId":"n5"},
  {"id":"b14","name":"Brickell City Centre","slug":"brickell-city-centre","neighborhoodId":"n5"},
  {"id":"b15","name":"Four Seasons","slug":"four-seasons","neighborhoodId":"n5"},
  {"id":"b16","name":"Santa Maria","slug":"santa-maria","neighborhoodId":"n5"},
  {"id":"b17","name":"SLS Brickell","slug":"sls-brickell","neighborhoodId":"n5"},
  {"id":"b18","name":"UNA Residences","slug":"una-residences","neighborhoodId":"n5"},
  {"id":"b19","name":"Panorama Tower","slug":"panorama-tower","neighborhoodId":"n5"},
  {"id":"b20","name":"Sail on Brickell","slug":"sail-on-brickell","neighborhoodId":"n5"},
  {"id":"b21","name":"Faena House","slug":"faena-house","neighborhoodId":"n18"},
  {"id":"b22","name":"Edition Residences","slug":"edition-residences","neighborhoodId":"n18"},
  {"id":"b23","name":"Bath Club","slug":"bath-club","neighborhoodId":"n18"},
  {"id":"b24","name":"Mosaic","slug":"mosaic","neighborhoodId":"n18"},
  {"id":"b25","name":"Fontainebleau Tresor","slug":"fontainebleau-tresor","neighborhoodId":"n18"},
  {"id":"b26","name":"La Gorce Palace","slug":"la-gorce-palace","neighborhoodId":"n18"},
  {"id":"b27","name":"Continuum North","slug":"continuum-north","neighborhoodId":"n22"},
  {"id":"b28","name":"Continuum South","slug":"continuum-south","neighborhoodId":"n22"},
  {"id":"b29","name":"Apogee","slug":"apogee","neighborhoodId":"n22"},
  {"id":"b30","name":"Murano Grande","slug":"murano-grande","neighborhoodId":"n22"},
  {"id":"b31","name":"Setai","slug":"setai","neighborhoodId":"n22"},
  {"id":"b32","name":"W South Beach","slug":"w-south-beach","neighborhoodId":"n22"},
  {"id":"b33","name":"Acqualina","slug":"acqualina","neighborhoodId":"n23"},
  {"id":"b34","name":"Jade Beach","slug":"jade-beach","neighborhoodId":"n23"},
  {"id":"b35","name":"Jade Ocean","slug":"jade-ocean","neighborhoodId":"n23"},
  {"id":"b36","name":"Porsche Design Tower","slug":"porsche-design-tower","neighborhoodId":"n23"},
  {"id":"b37","name":"Regalia","slug":"regalia","neighborhoodId":"n23"},
  {"id":"b38","name":"Trump Towers","slug":"trump-towers","neighborhoodId":"n23"},
  {"id":"b39","name":"Turnberry Ocean Colony","slug":"turnberry-ocean-colony","neighborhoodId":"n23"},
  {"id":"b40","name":"Sole on the Ocean","slug":"sole-on-the-ocean","neighborhoodId":"n23"},
  {"id":"b41","name":"HYDE Beach House","slug":"hyde-beach-house","neighborhoodId":"n15"}
]
